oogeso/__init__.py
oogeso/core/__init__.py
oogeso/core/devices/__init__.py
oogeso/core/devices/base.py
oogeso/core/devices/carbon_capture.py
oogeso/core/devices/compressor.py
oogeso/core/devices/electrolyser.py
oogeso/core/devices/fuelcell.py
oogeso/core/devices/gasheater.py
oogeso/core/devices/gasturbine.py
oogeso/core/devices/heatpump.py
oogeso/core/devices/pump.py
oogeso/core/devices/separator.py
oogeso/core/devices/sink.py
oogeso/core/devices/source.py
oogeso/core/devices/storage.py
oogeso/core/devices/well.py
oogeso/core/networks/__init__.py
oogeso/core/networks/edge.py
oogeso/core/networks/electricalsystem.py
oogeso/core/networks/electricity.py
oogeso/core/networks/network.py
oogeso/core/networks/network_node.py
oogeso/core/networks/pipelines.py
oogeso/core/optimiser.py
oogeso/core/simulator.py
oogeso/dto/__init__.py
oogeso/dto/base.py
oogeso/dto/carriers.py
oogeso/dto/devices.py
oogeso/dto/edges.py
oogeso/dto/mapper.py
oogeso/dto/serialisation.py
oogeso/dto/types.py
oogeso/io/__init__.py
oogeso/io/file_io.py
oogeso/plots/__init__.py
oogeso/plots/optimization_plots.py
oogeso/plots/plot_network.py
oogeso/plots/plots.py
oogeso/result_analysis.py
oogeso/utils/__init__.py
oogeso/utils/util.py
oogeso-1.6.0.dist-info/LICENSE
oogeso-1.6.0.dist-info/METADATA
oogeso-1.6.0.dist-info/WHEEL
oogeso-1.6.0.dist-info/RECORD
