Metadata-Version: 2.3
Name: oogeso
Version: 1.6.0
Summary: Offshore Oil and Gas Field Energy System Operational Optimisation (OOGESO)
License: MIT License (http://opensource.org/licenses/MIT)
Author: Harald Svendsen
Author-email: harald.svendsen@sintef.no
Requires-Python: >=3.9,<3.14
Classifier: Development Status :: 4 - Beta
Classifier: License :: OSI Approved :: MIT License
Classifier: License :: Other/Proprietary License
Classifier: Natural Language :: English
Classifier: Operating System :: MacOS
Classifier: Operating System :: Microsoft :: Windows
Classifier: Operating System :: POSIX :: Linux
Classifier: Programming Language :: Python :: 3
Classifier: Programming Language :: Python :: 3.9
Classifier: Programming Language :: Python :: 3.10
Classifier: Programming Language :: Python :: 3.11
Classifier: Programming Language :: Python :: 3.12
Classifier: Programming Language :: Python :: 3.13
Classifier: Topic :: Scientific/Engineering
Provides-Extra: plotting
Requires-Dist: PyYAML (>=6.0,<7.0)
Requires-Dist: Pyomo (>=6.7,<7.0)
Requires-Dist: fastparquet (>=2024,<2025)
Requires-Dist: ipython (>=8,<9) ; extra == "plotting"
Requires-Dist: ipywidgets (>=8,<9) ; extra == "plotting"
Requires-Dist: matplotlib (>=3.6,<4.0) ; extra == "plotting"
Requires-Dist: networkx (>=2.8,<3.0)
Requires-Dist: numpy (>=1.26,<2.0)
Requires-Dist: pandas (>=2.2,<3.0)
Requires-Dist: plotly (>=5.11,<6.0) ; extra == "plotting"
Requires-Dist: pydantic (>=1.9,<2.0)
Requires-Dist: pydot (>=2.0,<3.0)
Requires-Dist: scipy (>=1.9,<2.0)
Requires-Dist: seaborn (>=0.12,<0.13) ; extra == "plotting"
Requires-Dist: tqdm (>=4.62,<5.0)
Requires-Dist: webencodings (>=0.5.1,<0.6.0)
Requires-Dist: xlrd (>=2,<3)
Project-URL: Homepage, https://github.com/oogeso/oogeso
Project-URL: Repository, https://github.com/oogeso/oogeso
